{
    "name": "6669790b-7637511f",
    "frames": [
        {
            "timestamp": 10000,
            "objects": [
                {
                    "category": "traffic sign",
                    "id": 0,
                    "attributes": {
                        "occluded": false,
                        "truncated": false,
                        "trafficLightColor": "none"
                    },
                    "box2d": {
                        "x1": 633.49966,
                        "y1": 197.21744,
                        "x2": 662.954215,
                        "y2": 220.26883
                    }
                },
                {
                    "category": "traffic sign",
                    "id": 1,
                    "attributes": {
                        "occluded": false,
                        "truncated": false,
                        "trafficLightColor": "none"
                    },
                    "box2d": {
                        "x1": 889.626207,
                        "y1": 215.146299,
                        "x2": 930.606453,
                        "y2": 288.142365
                    }
                },
                {
                    "category": "traffic sign",
                    "id": 2,
                    "attributes": {
                        "occluded": false,
                        "truncated": false,
                        "trafficLightColor": "none"
                    },
                    "box2d": {
                        "x1": 890.906838,
                        "y1": 286.861734,
                        "x2": 921.642023,
                        "y2": 325.280718
                    }
                },
                {
                    "category": "traffic sign",
                    "id": 3,
                    "attributes": {
                        "occluded": false,
                        "truncated": false,
                        "trafficLightColor": "none"
                    },
                    "box2d": {
                        "x1": 817.910774,
                        "y1": 253.565283,
                        "x2": 872.977981,
                        "y2": 268.932877
                    }
                },
                {
                    "category": "traffic sign",
                    "id": 4,
                    "attributes": {
                        "occluded": false,
                        "truncated": false,
                        "trafficLightColor": "none"
                    },
                    "box2d": {
                        "x1": 860.171654,
                        "y1": 276.61667,
                        "x2": 880.661777,
                        "y2": 293.264896
                    }
                },
                {
                    "category": "traffic sign",
                    "id": 5,
                    "attributes": {
                        "occluded": false,
                        "truncated": false,
                        "trafficLightColor": "none"
                    },
                    "box2d": {
                        "x1": 870.416715,
                        "y1": 297.106795,
                        "x2": 893.468105,
                        "y2": 325.280718
                    }
                },
                {
                    "category": "traffic light",
                    "id": 6,
                    "attributes": {
                        "occluded": false,
                        "truncated": false,
                        "trafficLightColor": "green"
                    },
                    "box2d": {
                        "x1": 424.756525,
                        "y1": 269.786626,
                        "x2": 451.64981,
                        "y2": 300.521812
                    }
                },
                {
                    "category": "traffic light",
                    "id": 7,
                    "attributes": {
                        "occluded": false,
                        "truncated": false,
                        "trafficLightColor": "green"
                    },
                    "box2d": {
                        "x1": 796.140018,
                        "y1": 255.699666,
                        "x2": 814.068876,
                        "y2": 282.592954
                    }
                },
                {
                    "category": "traffic light",
                    "id": 8,
                    "attributes": {
                        "occluded": false,
                        "truncated": false,
                        "trafficLightColor": "green"
                    },
                    "box2d": {
                        "x1": 864.013551,
                        "y1": 310.766874,
                        "x2": 880.661777,
                        "y2": 323.573202
                    }
                },
                {
                    "category": "car",
                    "id": 9,
                    "attributes": {
                        "occluded": true,
                        "truncated": false,
                        "trafficLightColor": "none"
                    },
                    "box2d": {
                        "x1": 785.881649,
                        "y1": 341.928939,
                        "x2": 802.529874,
                        "y2": 358.577165
                    }
                },
                {
                    "category": "car",
                    "id": 10,
                    "attributes": {
                        "occluded": true,
                        "truncated": false,
                        "trafficLightColor": "none"
                    },
                    "box2d": {
                        "x1": 770.514055,
                        "y1": 341.928939,
                        "x2": 787.16228,
                        "y2": 361.138433
                    }
                },
                {
                    "category": "car",
                    "id": 11,
                    "attributes": {
                        "occluded": true,
                        "truncated": false,
                        "trafficLightColor": "none"
                    },
                    "box2d": {
                        "x1": 755.146462,
                        "y1": 343.209573,
                        "x2": 775.636585,
                        "y2": 363.699696
                    }
                },
                {
                    "category": "car",
                    "id": 12,
                    "attributes": {
                        "occluded": true,
                        "truncated": false,
                        "trafficLightColor": "none"
                    },
                    "box2d": {
                        "x1": 737.217603,
                        "y1": 344.490206,
                        "x2": 764.110891,
                        "y2": 366.260962
                    }
                },
                {
                    "category": "car",
                    "id": 13,
                    "attributes": {
                        "occluded": true,
                        "truncated": false,
                        "trafficLightColor": "none"
                    },
                    "box2d": {
                        "x1": 725.691909,
                        "y1": 349.612737,
                        "x2": 750.02393,
                        "y2": 366.260962
                    }
                },
                {
                    "category": "car",
                    "id": 14,
                    "attributes": {
                        "occluded": true,
                        "truncated": false,
                        "trafficLightColor": "none"
                    },
                    "box2d": {
                        "x1": 694.956724,
                        "y1": 347.05147,
                        "x2": 737.217603,
                        "y2": 367.541593
                    }
                },
                {
                    "category": "car",
                    "id": 15,
                    "attributes": {
                        "occluded": true,
                        "truncated": false,
                        "trafficLightColor": "none"
                    },
                    "box2d": {
                        "x1": 679.589132,
                        "y1": 350.89337,
                        "x2": 719.288747,
                        "y2": 375.22539
                    }
                },
                {
                    "category": "car",
                    "id": 16,
                    "attributes": {
                        "occluded": true,
                        "truncated": false,
                        "trafficLightColor": "none"
                    },
                    "box2d": {
                        "x1": 628.363822,
                        "y1": 347.05147,
                        "x2": 693.676093,
                        "y2": 381.628553
                    }
                },
                {
                    "category": "car",
                    "id": 17,
                    "attributes": {
                        "occluded": true,
                        "truncated": false,
                        "trafficLightColor": "none"
                    },
                    "box2d": {
                        "x1": 802.529873,
                        "y1": 338.087042,
                        "x2": 856.316447,
                        "y2": 363.699698
                    }
                },
                {
                    "category": "car",
                    "id": 18,
                    "attributes": {
                        "occluded": false,
                        "truncated": false,
                        "trafficLightColor": "none"
                    },
                    "box2d": {
                        "x1": 797.407342,
                        "y1": 339.794556,
                        "x2": 953.644536,
                        "y2": 434.561378
                    }
                },
                {
                    "category": "car",
                    "id": 19,
                    "attributes": {
                        "occluded": false,
                        "truncated": false,
                        "trafficLightColor": "none"
                    },
                    "box2d": {
                        "x1": 538.71953,
                        "y1": 344.917086,
                        "x2": 659.099007,
                        "y2": 447.367704
                    }
                },
                {
                    "category": "car",
                    "id": 20,
                    "attributes": {
                        "occluded": true,
                        "truncated": false,
                        "trafficLightColor": "none"
                    },
                    "box2d": {
                        "x1": 432.853864,
                        "y1": 353.881517,
                        "x2": 532.743218,
                        "y2": 392.3005
                    }
                },
                {
                    "category": "car",
                    "id": 21,
                    "attributes": {
                        "occluded": true,
                        "truncated": false,
                        "trafficLightColor": "none"
                    },
                    "box2d": {
                        "x1": 423.889436,
                        "y1": 369.249109,
                        "x2": 464.869682,
                        "y2": 399.984292
                    }
                },
                {
                    "category": "car",
                    "id": 22,
                    "attributes": {
                        "occluded": true,
                        "truncated": false,
                        "trafficLightColor": "none"
                    },
                    "box2d": {
                        "x1": 381.628556,
                        "y1": 371.810374,
                        "x2": 432.853866,
                        "y2": 408.948722
                    }
                },
                {
                    "category": "car",
                    "id": 23,
                    "attributes": {
                        "occluded": false,
                        "truncated": false,
                        "trafficLightColor": "none"
                    },
                    "box2d": {
                        "x1": 162.989631,
                        "y1": 337.062542,
                        "x2": 413.9005,
                        "y2": 487.240735
                    }
                },
                {
                    "category": "car",
                    "id": 24,
                    "attributes": {
                        "occluded": true,
                        "truncated": false,
                        "trafficLightColor": "none"
                    },
                    "box2d": {
                        "x1": 785.540123,
                        "y1": 360.113931,
                        "x2": 817.55594,
                        "y2": 393.410382
                    }
                },
                {
                    "category": "traffic sign",
                    "id": 25,
                    "attributes": {
                        "occluded": false,
                        "truncated": false,
                        "trafficLightColor": "none"
                    },
                    "box2d": {
                        "x1": 483.439632,
                        "y1": 28.678622,
                        "x2": 517.239437,
                        "y2": 47.114879
                    }
                },
                {
                    "category": "bus",
                    "id": 26,
                    "attributes": {
                        "occluded": true,
                        "truncated": false,
                        "trafficLightColor": "none"
                    },
                    "box2d": {
                        "x1": 673.947624,
                        "y1": 289.858931,
                        "x2": 744.619942,
                        "y2": 322.6345
                    }
                },
                {
                    "category": "area/drivable",
                    "id": 27,
                    "attributes": {},
                    "poly2d": [
                        [
                            525.917661,
                            459.055264,
                            "L"
                        ],
                        [
                            745.46583,
                            459.055264,
                            "L"
                        ],
                        [
                            852.246079,
                            532.903285,
                            "L"
                        ],
                        [
                            699.560305,
                            522.923823,
                            "C"
                        ],
                        [
                            590.784165,
                            523.921769,
                            "C"
                        ],
                        [
                            449.075802,
                            528.9115,
                            "C"
                        ],
                        [
                            525.917661,
                            459.055264,
                            "L"
                        ]
                    ]
                },
                {
                    "category": "area/alternative",
                    "id": 28,
                    "attributes": {},
                    "poly2d": [
                        [
                            860.229647,
                            444.08607,
                            "L"
                        ],
                        [
                            948.048915,
                            427.120986,
                            "L"
                        ],
                        [
                            1280.36501,
                            474.024458,
                            "L"
                        ],
                        [
                            1280.36501,
                            533.901231,
                            "L"
                        ],
                        [
                            1203.523149,
                            530.907393,
                            "L"
                        ],
                        [
                            860.229647,
                            444.08607,
                            "L"
                        ]
                    ]
                },
                {
                    "category": "lane/single white",
                    "id": 29,
                    "attributes": {
                        "direction": "parallel",
                        "style": "solid"
                    },
                    "poly2d": [
                        [
                            545.134101,
                            446.843305,
                            "L"
                        ],
                        [
                            445.323739,
                            535.904858,
                            "L"
                        ]
                    ]
                },
                {
                    "category": "lane/single white",
                    "id": 30,
                    "attributes": {
                        "direction": "parallel",
                        "style": "solid"
                    },
                    "poly2d": [
                        [
                            538.991925,
                            439.165585,
                            "L"
                        ],
                        [
                            420.755037,
                            534.369315,
                            "L"
                        ]
                    ]
                },
                {
                    "category": "lane/single white",
                    "id": 31,
                    "attributes": {
                        "direction": "parallel",
                        "style": "solid"
                    },
                    "poly2d": [
                        [
                            715.579486,
                            423.810145,
                            "L"
                        ],
                        [
                            896.773678,
                            531.298226,
                            "L"
                        ]
                    ]
                },
                {
                    "category": "lane/single white",
                    "id": 32,
                    "attributes": {
                        "direction": "parallel",
                        "style": "solid"
                    },
                    "poly2d": [
                        [
                            700.224044,
                            423.810145,
                            "L"
                        ],
                        [
                            852.242902,
                            535.904858,
                            "L"
                        ]
                    ]
                },
                {
                    "category": "lane/single white",
                    "id": 33,
                    "attributes": {
                        "direction": "parallel",
                        "style": "solid"
                    },
                    "poly2d": [
                        [
                            750.896998,
                            423.810145,
                            "L"
                        ],
                        [
                            1191.598127,
                            529.762681,
                            "L"
                        ]
                    ]
                },
                {
                    "category": "lane/single white",
                    "id": 34,
                    "attributes": {
                        "direction": "parallel",
                        "style": "solid"
                    },
                    "poly2d": [
                        [
                            746.290364,
                            428.416777,
                            "L"
                        ],
                        [
                            1174.707143,
                            537.440402,
                            "L"
                        ]
                    ]
                },
                {
                    "category": "lane/single white",
                    "id": 35,
                    "attributes": {
                        "direction": "parallel",
                        "style": "solid"
                    },
                    "poly2d": [
                        [
                            1000.565073,
                            433.304528,
                            "L"
                        ],
                        [
                            1280.643701,
                            472.947552,
                            "L"
                        ]
                    ]
                },
                {
                    "category": "lane/single white",
                    "id": 36,
                    "attributes": {
                        "direction": "parallel",
                        "style": "solid"
                    },
                    "poly2d": [
                        [
                            268.068141,
                            471.764989,
                            "L"
                        ],
                        [
                            0,
                            534.369315,
                            "L"
                        ]
                    ]
                },
                {
                    "category": "lane/road curb",
                    "id": 37,
                    "attributes": {
                        "direction": "parallel",
                        "style": "solid"
                    },
                    "poly2d": [
                        [
                            184.154412,
                            447.290151,
                            "L"
                        ],
                        [
                            0,
                            492.909627,
                            "L"
                        ]
                    ]
                },
                {
                    "category": "lane/single white",
                    "id": 38,
                    "attributes": {
                        "direction": "vertical",
                        "style": "solid"
                    },
                    "poly2d": [
                        [
                            410.006229,
                            433.023408,
                            "L"
                        ],
                        [
                            545.134101,
                            428.416777,
                            "L"
                        ]
                    ]
                },
                {
                    "category": "lane/single white",
                    "id": 39,
                    "attributes": {
                        "direction": "vertical",
                        "style": "solid"
                    },
                    "poly2d": [
                        [
                            542.063012,
                            423.810145,
                            "L"
                        ],
                        [
                            426.897213,
                            426.881232,
                            "L"
                        ]
                    ]
                },
                {
                    "category": "lane/single white",
                    "id": 40,
                    "attributes": {
                        "direction": "vertical",
                        "style": "solid"
                    },
                    "poly2d": [
                        [
                            545.134101,
                            417.667969,
                            "L"
                        ],
                        [
                            431.503844,
                            420.739056,
                            "L"
                        ]
                    ]
                },
                {
                    "category": "lane/single white",
                    "id": 41,
                    "attributes": {
                        "direction": "vertical",
                        "style": "solid"
                    },
                    "poly2d": [
                        [
                            652.62218,
                            423.810145,
                            "L"
                        ],
                        [
                            804.641036,
                            420.739056,
                            "L"
                        ]
                    ]
                },
                {
                    "category": "lane/single white",
                    "id": 42,
                    "attributes": {
                        "direction": "vertical",
                        "style": "solid"
                    },
                    "poly2d": [
                        [
                            798.49886,
                            416.132425,
                            "L"
                        ],
                        [
                            652.62218,
                            417.667969,
                            "L"
                        ]
                    ]
                },
                {
                    "category": "lane/single white",
                    "id": 43,
                    "attributes": {
                        "direction": "vertical",
                        "style": "solid"
                    },
                    "poly2d": [
                        [
                            792.356686,
                            409.990249,
                            "L"
                        ],
                        [
                            652.62218,
                            411.525793,
                            "L"
                        ]
                    ]
                }
            ]
        }
    ],
    "attributes": {
        "weather": "clear",
        "scene": "highway",
        "timeofday": "night"
    }
}